LICENSE
MANIFEST.in
README.md
change.log
setup.py
django_pims.egg-info/PKG-INFO
django_pims.egg-info/SOURCES.txt
django_pims.egg-info/dependency_links.txt
django_pims.egg-info/requires.txt
django_pims.egg-info/top_level.txt
private_info/__init__.py
private_info/admin.py
private_info/apps.py
private_info/forms.py
private_info/models.py
private_info/tests.py
private_info/urls.py
private_info/utils.py
private_info/views.py
private_info/migrations/0001_initial.py
private_info/migrations/0002_auto_20220726_1419.py
private_info/migrations/0003_auto_20220728_1548.py
private_info/migrations/0004_auto_20220729_2008.py
private_info/migrations/__init__.py
private_info/static/boot/css/bootstrap.min.css
private_info/static/boot/js/bootstrap.bundle.min.js
private_info/static/private_info/css/dashboard.css
private_info/static/private_info/css/sidebars.css
private_info/static/private_info/css/sticky-footer-navbar.css
private_info/static/private_info/js/curd.js
private_info/static/private_info/js/dashboard.js
private_info/templates/private_info/chpass.html
private_info/templates/private_info/login.html
private_info/templates/private_info/login_base.html
private_info/templates/private_info/main-base.html
private_info/templates/private_info/main-data-auth.html
private_info/templates/private_info/main-data-delete.html
private_info/templates/private_info/main-data-display.html
private_info/templates/private_info/main-data-modify.html
private_info/templates/private_info/main-data-new.html
private_info/templates/private_info/main-data.html
private_info/templates/private_info/main-password-auth.html
private_info/templates/private_info/main-password-display.html
private_info/templates/private_info/main-password-modify.html
private_info/templates/private_info/main-password-new.html
private_info/templates/private_info/main-password.html
private_info/templates/private_info/registry.html