Metadata-Version: 2.1
Name: django-pims
Version: 1.0.1
Summary: A django app for manage ypur private info.
Home-page: https://github.com/rwxhc/django-pims
Author: Huang Cheng
Author-email: wsjhhc@tom.com
License: Free
License-File: LICENSE
